Metadata-Version: 2.1
Name: streamlit-aggrid-bugfix
Version: 0.3.4.post4
Summary: Streamlit component implementation of ag-grid
Home-page: https://github.com/PablocFonseca/streamlit-aggrid
Author: Gene Ruebsamen
Author-email: ruebsamen.gene@gmail.com
Requires-Python: >=3.8
Classifier: License :: OSI Approved :: MIT License
Classifier: Operating System :: OS Independent
Classifier: Programming Language :: Python :: 3
Classifier: Programming Language :: Python :: 3.8
Classifier: Programming Language :: Python :: 3.9
Classifier: Programming Language :: Python :: 3.10
Classifier: Programming Language :: Python :: 3.11
Classifier: Programming Language :: Python :: 3
Requires-Dist: pandas (>=1.2)
Requires-Dist: python-decouple (>=3.6,<4.0)
Requires-Dist: streamlit (>=0.87.0)
